{
  "category": "bewitchment:curses",
  "name": "Солнечная Болезнь",
  "icon": "minecraft:sunflower",
  "advancement": "minecraft:nether/find_fortress",
  "pages": [
	{
	  "type": "patchouli:text",
	  "text": "Ослабляя кожу цели, это $(l:bewitchment:curses/conducting_curses) Проклятие$() делает их чрезвычайно восприимчивыми к солнечному свету. $(br2) На самом деле солнце буквально поджигает проклятую цель."
	},
	{
	  "type": "bewitchment:curse",
	  "recipe": "bewitchment:curses/solar_hatred"
	}
  ]
}
