{
  "category": "bewitchment:sigils",
  "name": "using sigils",
  "icon": "bewitchment:mending_sigil",
  "advancement": "minecraft:nether/find_fortress",
  "priority": true,
  "pages": [
	{
	  "type": "text",
	  "text": "sigils are magic symbols of power. they can be divided into two groups: active and passive sigils.$(br2)active sigils need to be placed on usable blocks or brooms made from dragon's blood.$(br2)passive sigils can be placed anywhere and will apply their effect to everything around."
	},
	{
	  "type": "text",
	  "text": "it should be noted that all sigils are of limited duration.$(br2)taglocks can be added to sigils to control who it affects. if a sigil is set to regard the taglocks as a whitelist, the sigil will only affect those in it. if it is set as a blacklist, the sigil won't affect anyone the taglock is from.$(br2)use an athame while sneaking to toggle between blacklist and whitelist."
	}
  ]
}
