{
  "category": "bewitchment:tools",
  "name": "Candelabras",
  "icon": "bewitchment:iron_candelabra",
  "pages": [
    {
      "type": "text",
      "text": "can be lit with flint and steel\nwhen lit, repels ghosts (strenth based on material)"
    },
    {
      "type": "crafting",
      "recipe": "bewitchment:iron_candelabra"
    },
    {
      "type": "crafting",
      "recipe": "bewitchment:golden_candelabra"
    },
    {
      "type": "crafting",
      "recipe": "bewitchment:silver_candelabra"
    },
    {
      "type": "crafting",
      "recipe": "bewitchment:netherite_candelabra"
    }
  ]
}